<?xml version="1.0" encoding="UTF-8" standalone="yes"?>
<users>
  <users>
    <email>e1@emp.com</email>
    <password>e1</password>
    <wage>90000.50</wage>
    <role>EMPLOYEE</role>
  </users>
  <users>
    <email>e2@emp.com</email>
    <password>e2</password>
    <wage>90000.50</wage>
    <role>EMPLOYEE</role>
  </users>
  <users>
    <email>s1@sup.com</email>
    <password>s1</password>
    <wage>100000</wage>
    <role>SUPERVISOR</role>
  </users>
  <users>
    <email>ent1@ent.com</email>
    <password>ent1</password>
    <wage>0</wage>
    <role>ENTERPRISE</role>
  </users>
</users>
